cdk_cloudformation_newrelic_observability_dashboards/__init__.py
cdk_cloudformation_newrelic_observability_dashboards/py.typed
cdk_cloudformation_newrelic_observability_dashboards/_jsii/__init__.py
cdk_cloudformation_newrelic_observability_dashboards/_jsii/newrelic-observability-dashboards@1.2.0-alpha.7.jsii.tgz
cdk_cloudformation_newrelic_observability_dashboards-1.2.0a7.dist-info/LICENSE
cdk_cloudformation_newrelic_observability_dashboards-1.2.0a7.dist-info/METADATA
cdk_cloudformation_newrelic_observability_dashboards-1.2.0a7.dist-info/WHEEL
cdk_cloudformation_newrelic_observability_dashboards-1.2.0a7.dist-info/top_level.txt
cdk_cloudformation_newrelic_observability_dashboards-1.2.0a7.dist-info/RECORD
